asyncchain/__init__.py
asyncchain-0.1.1.dist-info/LICENSE
asyncchain-0.1.1.dist-info/WHEEL
asyncchain-0.1.1.dist-info/METADATA
asyncchain-0.1.1.dist-info/RECORD
